{
  "_format": "hh-sol-cache-2",
  "files": {
    "/Users/macbook/Desktop/cryptonTestTask/contracts/task2.sol": {
      "lastModificationDate": 1656114227876,
      "contentHash": "8149209d7996f8f75f8c7993c642eb06",
      "sourceName": "contracts/task2.sol",
      "solcConfig": {
        "version": "0.8.13",
        "settings": {
          "optimizer": {
            "enabled": false,
            "runs": 200
          },
          "outputSelection": {
            "*": {
              "*": [
                "abi",
                "evm.bytecode",
                "evm.deployedBytecode",
                "evm.methodIdentifiers",
                "metadata"
              ],
              "": [
                "ast"
              ]
            }
          },
          "metadata": {
            "useLiteralContent": false
          }
        }
      },
      "imports": [],
      "versionPragmas": [
        "^0.8.13"
      ],
      "artifacts": [
        "Voting"
      ]
    }
  }
}
